{
  "source": "Pancavamsa Brahmana",
  "translator": "W. Caland",
  "publication_date": 1931,
  "extraction_date": "2026-01-31",
  "categorized_nouns": {
    "deity_names": [
      "Aditya",
      "Agni",
      "Agni sometimes is identified with Rudra",
      "Agnistut",
      "Aryaman",
      "Bhaga",
      "Brahma",
      "Brahmanaspati",
      "Indra",
      "Indra agreed and",
      "Indra and Sumitra",
      "Marut",
      "Mitra",
      "Parjanya",
      "Prajapati to Indra",
      "Rudra",
      "Soma",
      "Surya",
      "Varuna",
      "Vata",
      "Yama",
      "and Mitra",
      "arrow shot by Rudra",
      "as Indra",
      "beside Mitra",
      "left over by the Brahmanacchamsin",
      "of Indra",
      "of Soma",
      "of Soma running through the strainer into the dronakalasa",
      "paryasa addressed to Indra",
      "steeds of Indra",
      "the Adityas",
      "the Agnidhra",
      "the Brahmanacchamsin",
      "the Maruts",
      "the Soma",
      "the author of the Brahmana",
      "the chant of Yama",
      "the words of the Brahman a",
      "to Agni",
      "to Indra",
      "who follows our Brahmana"
    ],
    "sage_names": [
      "Angiras",
      "Apastamba",
      "Atharvans",
      "Baudhayana",
      "Gobhila",
      "Kanva",
      "Katyayana",
      "Manava",
      "Paijavana",
      "Svitra the Angiras",
      "Vamadeva",
      "Visvamitra",
      "chant of the Angirases",
      "the Atharvans",
      "to the other Angirases"
    ],
    "ritual_names": [
      "Aptoryama"
    ],
    "location_names": [],
    "sakha_names": [],
    "uncategorized": []
  },
  "section_statistics": {
    "total_sections": 342,
    "sections": [
      "THE BOOK WAS",
      "This book should be returned on or before the date last marked belowi",
      "CHAPTERS",
      "Chapter 7. The Samavedic Texts.",
      "of the books belonging to the Samaveda.",
      "^ With reference to the books of the Jaiminiyas, my Introduction to the edition",
      "li INTRODUCTION, CHAPTER I, ยง 1.",
      "in 26 chapters (prapathakas), published together with the commentary",
      "Regarding this Brahmana see below, chapter III.",
      "appendix to the preceding, reckoned as its 26th book. It has been"
    ]
  },
  "notes": "Preliminary extraction. Requires manual review and categorization for accurate integration into proper noun variants database."
}